ape_scroll/__init__.py
ape_scroll/ecosystem.py
ape_scroll/py.typed
ape_scroll/version.py
ape_scroll-0.4.1.dist-info/LICENSE
ape_scroll-0.4.1.dist-info/METADATA
ape_scroll-0.4.1.dist-info/WHEEL
ape_scroll-0.4.1.dist-info/top_level.txt
ape_scroll-0.4.1.dist-info/RECORD
